pycnet/TestPycnet.py
pycnet/__init__.py
pycnet/__main__.py
pycnet/cnet/PNW-Cnet_v4_TF.h5
pycnet/cnet/PNW-Cnet_v5_TF.h5
pycnet/cnet/__init__.py
pycnet/cnet/target_classes.csv
pycnet/file/__init__.py
pycnet/file/image.py
pycnet/file/wav.py
pycnet/plot/__init__.py
pycnet/process/__init__.py
pycnet/prog/__init__.py
pycnet/review/__init__.py
pycnet_audio-0.5.11.dist-info/licenses/LICENSE.md
pycnet_audio-0.5.11.dist-info/METADATA
pycnet_audio-0.5.11.dist-info/WHEEL
pycnet_audio-0.5.11.dist-info/entry_points.txt
pycnet_audio-0.5.11.dist-info/top_level.txt
pycnet_audio-0.5.11.dist-info/RECORD
