Metadata-Version: 2.4
Name: pycnet-audio
Version: 0.5.11
Summary: Audio processing with PNW-Cnet
Author-email: Zack Ruff <zjruff@gmail.com>
Maintainer-email: Zack Ruff <zjruff@gmail.com>
License:                     GNU GENERAL PUBLIC LICENSE
Project-URL: Documentation, https://pycnet-audio.readthedocs.io/
Project-URL: Repository, https://github.com/zjruff/pycnet-audio
Project-URL: Issues, https://github.com/zjruff/pycnet-audio/issues
Keywords: bioacoustics,deep learning,ecology
Classifier: Development Status :: 4 - Beta
Classifier: Intended Audience :: Science/Research
Classifier: Programming Language :: Python :: 3
Classifier: Programming Language :: Python :: 3.8
Classifier: License :: OSI Approved :: GNU General Public License v3 (GPLv3)
Classifier: Operating System :: OS Independent
Requires-Python: <3.12,>=3.8
License-File: LICENSE.md
Requires-Dist: tensorflow-cpu<2.14
Requires-Dist: pillow
Requires-Dist: pandas
Requires-Dist: scipy
Requires-Dist: seaborn
Requires-Dist: matplotlib
Dynamic: license-file
